delete_substring/__init__.py
delete_substring-0.9.6.dist-info/LICENSE
delete_substring-0.9.6.dist-info/METADATA
delete_substring-0.9.6.dist-info/WHEEL
delete_substring-0.9.6.dist-info/top_level.txt
delete_substring-0.9.6.dist-info/RECORD
