Metadata-Version: 2.1
Name: delete-substring
Version: 0.9.6
Summary: Simple library for delete substring
Home-page: 
Author: 
Author-email: 
License: UNKNOWN
Platform: UNKNOWN
Classifier: Programming Language :: Python :: 3
Classifier: License :: OSI Approved :: MIT License
Classifier: Operating System :: OS Independent
Requires-Python: >=3.6
License-File: LICENSE
